{
    "age": "العمر",
    "email": "الايميل",
    "address": "العنوان",
    "freelance": "Freelance",
    "language": "اللغه",
    "experienceCount": "سنوات الخبره",
    "contactMe": "تواصل معي",
    "getInTouch": "ابقى على تواصل",
    "name": "وافي اليوسفي",
    "position": "خريج تقنية المعلومات",
    "skill": "تقنية المعلومات، تطوير الويب، هندسة البرمجيات",
    "experience": "تجربة عملية ومشاريع في مجال تقنية المعلومات",
    "passion": "استكشاف التقنيات الجديدة وحل المشاكل الواقعية",
    "home": "الرئيسية",
    "about": "حول",
    "portfolio": "المحفظة",
    "skills": "المهارات",
    "contact": "اتصل",
    "hi": "مرحبًا، أنا وافي اليوسفي",
    "developer": "مطور واجهة ومطور خلفية",
    "aboutBtn": "عني",
    "title": "المحفظة",
    "heading": "عملي",
    "my": "عملي",
    "loadMore": "تحميل المزيد",
    "projectTitle1": "المشروع 01",
    "projectTitle2": "المشروع 02",
    "projectTitle3": "المشروع 03",
    "projectTitle4": "المشروع 04",
    "projectTitle5": "المشروع 05",
    "projectTitle6": "المشروع 06",
    "projectDesc1": "تشات جي بي تي - افتح الذكاء الاصطناعي - نموذج HTML5 - يصدر الحيوان من 'Polar Games' المطور 'وافي اليوسفي'.",
    "projectDesc2": "تم إنشاء قالب التجارة الإلكترونية الخاص بنا بسرعة فائقة لمساعدة أي شخص في بدء متجره الإلكتروني الخاص بسهولة. بُنيت بواسطة React.",
    "projectDesc3": "هدف InfyCare هو إدارة حجز موعدك في المستشفى رقميًا.",
    "projectDesc4": "لوريم، ipsum dolor sit amet consectetur adipisicing elit. Distinctio, praesentium.",
    "projectDesc5": "يوفر ميزات مدرسة إلكترونية. إذا كان لديك أي أسئلة، فلا تتردد في التواصل. شكرًا لاختيار مدرسة إلكترونية!",
    "projectDesc6": "منصة بيع دورات عبر الإنترنت وبيع الكتب الإلكترونية في مكان واحد",
    "readMore": "اقرأ المزيد"
}